calligator/__init__.py
calligator/boards.py
calligator/cameras.py
calligator/utils.py
calligator-0.3.2.dist-info/LICENSE
calligator-0.3.2.dist-info/METADATA
calligator-0.3.2.dist-info/WHEEL
calligator-0.3.2.dist-info/top_level.txt
calligator-0.3.2.dist-info/RECORD
