Metadata-Version: 2.1
Name: calligator
Version: 0.3.2
Summary: An easy-to-use library for calibrating cameras in python
Home-page: https://github.com/lambdaloop/calligator
Author: Pierre Karashchuk
Author-email: krchtchk@gmail.com
License: UNKNOWN
Platform: UNKNOWN
Classifier: Programming Language :: Python :: 3
Classifier: License :: OSI Approved :: BSD License
Classifier: Intended Audience :: Science/Research
Classifier: Topic :: Scientific/Engineering
Classifier: Topic :: Scientific/Engineering :: Image Recognition
Requires-Dist: numba
Requires-Dist: numpy
Requires-Dist: opencv-contrib-python (~=3.4)
Requires-Dist: opencv-python (~=3.4)
Requires-Dist: scipy
Requires-Dist: toml
Provides-Extra: full
Requires-Dist: checkerboard ; extra == 'full'
